pyupload/__init__.py
pyupload/main.py
pyupload/tests/__init__.py
pyupload/tests/upload_test.py
pyupload/uploader/__init__.py
pyupload/uploader/base.py
pyupload/uploader/catbox.py
pyupload/uploader/fileio.py
pyupload/uploader/mixtape.py
pyupload/uploader/uguu.py
PyUpload-0.1.4.dist-info/LICENSE
PyUpload-0.1.4.dist-info/METADATA
PyUpload-0.1.4.dist-info/WHEEL
PyUpload-0.1.4.dist-info/entry_points.txt
PyUpload-0.1.4.dist-info/top_level.txt
PyUpload-0.1.4.dist-info/RECORD
