Metadata-Version: 2.1
Name: PyUpload
Version: 0.1.4
Summary: A simple CLI tool to upload file with direct link
Home-page: https://github.com/yukinotenshi/pyupload
Author: yukinotenshi
Author-email: gabriel.bentara@gmail.com
License: MIT
Keywords: direct upload cli
Platform: UNKNOWN
